setup.py
update_pypi_script.sh
NamedMatrix.egg-info/PKG-INFO
NamedMatrix.egg-info/SOURCES.txt
NamedMatrix.egg-info/dependency_links.txt
NamedMatrix.egg-info/requires.txt
NamedMatrix.egg-info/top_level.txt
namedmatrix/NamedMatrix.py
namedmatrix/__init__.py
namedmatrix/maxdotmodule.c