Metadata-Version: 1.0
Name: NamedMatrix
Version: 0.9dev
Summary: NamedMatrix, a numpy matrix wrapper class.
Home-page: http://www-helix.stanford.edu
Author: Nicholas P. Tatonetti & Guy Haskin Fernald
Author-email: nick.tatonetti@stanford.edu & guyhf@stanford.edu
License: UNKNOWN
Platform: UNKNOWN
